tcabci_read_client/__init__.py
tcabci_read_client/client.py
tests/__init__.py
tests/test_httpclient.py
tests/test_websocket.py
tcabci_read_client-0.1.5.dist-info/LICENSE
tcabci_read_client-0.1.5.dist-info/METADATA
tcabci_read_client-0.1.5.dist-info/WHEEL
tcabci_read_client-0.1.5.dist-info/top_level.txt
tcabci_read_client-0.1.5.dist-info/RECORD
