Metadata-Version: 2.1
Name: tcabci-read-client
Version: 0.1.5
Summary: transferchain abci read client
Home-page: https://github.com/transferchain/tcabci-read-python-client
Author: transferchain
Requires-Python: >=3.8
License-File: LICENSE
Requires-Dist: requests ==2.31.0
Requires-Dist: websockets ==11.0.3
Requires-Dist: websocket-client ==1.6.3
